[
  {
    "id": "mubi_gianfranco-rosi",
    "title": "Gianfranco Rosi",
    "year": null,
    "director": "",
    "country": "",
    "country_flag": "",
    "synopsis": "",
    "thumbnail": "",
    "url": "https://mubi.com/en/jp/films/gianfranco-rosi",
    "source": "MUBI",
    "expires_at": "2026-04-27T21:09:30.214621+00:00",
    "fetched_at": "2026-03-28T21:09:30.214621+00:00",
    "comment": "ヴェネチア国際映画祭で金獅子賞を受賞したジャンフランコ・ロッシの本作は、難民キャンプやスラム街を舞台にした彼の社会派ドキュメンタリーの系譜を受け継ぎながら、より個人的な視点へと内省を深めた作品として位置づけられる。グローバル化の光と影を映像詩的に凝視する手法は、境界や分断が深刻化する現代において、我々が見落としてきた人間の尊厳と共存の可能性を問い直させる。時代の急速な変化のなかで、映像による「目撃」の倫理的意義を改めて考えさせる傑作である。",
    "score": 0.0
  }
]